streamlit_lang_tts/__init__.py
streamlit_lang_tts/frontend/build/asset-manifest.json
streamlit_lang_tts/frontend/build/bootstrap.min.css
streamlit_lang_tts/frontend/build/index.html
streamlit_lang_tts/frontend/build/static/js/2.38865783.chunk.js
streamlit_lang_tts/frontend/build/static/js/2.38865783.chunk.js.LICENSE.txt
streamlit_lang_tts/frontend/build/static/js/2.38865783.chunk.js.map
streamlit_lang_tts/frontend/build/static/js/2.cfa3d2aa.chunk.js
streamlit_lang_tts/frontend/build/static/js/2.cfa3d2aa.chunk.js.LICENSE.txt
streamlit_lang_tts/frontend/build/static/js/2.cfa3d2aa.chunk.js.map
streamlit_lang_tts/frontend/build/static/js/2.d7bda64d.chunk.js
streamlit_lang_tts/frontend/build/static/js/2.d7bda64d.chunk.js.LICENSE.txt
streamlit_lang_tts/frontend/build/static/js/2.d7bda64d.chunk.js.map
streamlit_lang_tts/frontend/build/static/js/main.2cce2544.chunk.js
streamlit_lang_tts/frontend/build/static/js/main.2cce2544.chunk.js.map
streamlit_lang_tts/frontend/build/static/js/main.78d08be9.chunk.js
streamlit_lang_tts/frontend/build/static/js/main.78d08be9.chunk.js.map
streamlit_lang_tts/frontend/build/static/js/main.d75feb69.chunk.js
streamlit_lang_tts/frontend/build/static/js/main.d75feb69.chunk.js.map
streamlit_lang_tts/frontend/build/static/js/runtime-main.0a6aa703.js
streamlit_lang_tts/frontend/build/static/js/runtime-main.0a6aa703.js.map
streamlit_lang_tts-0.0.5.dist-info/LICENSE
streamlit_lang_tts-0.0.5.dist-info/METADATA
streamlit_lang_tts-0.0.5.dist-info/WHEEL
streamlit_lang_tts-0.0.5.dist-info/top_level.txt
streamlit_lang_tts-0.0.5.dist-info/RECORD
