Metadata-Version: 2.1
Name: streamlit-lang-tts
Version: 0.0.5
Summary: Streamlit extensions for text-to-speech
Home-page: 
Author: Ryan Rapp
Author-email: skies_midair0f@icloud.com
Requires-Python: >=3.6
License-File: LICENSE
Requires-Dist: streamlit (>=0.63)
